ws_api/__init__.py
ws_api/exceptions.py
ws_api/session.py
ws_api/wealthsimple_api.py
ws_api-0.25.0.dist-info/licenses/LICENSE
ws_api-0.25.0.dist-info/METADATA
ws_api-0.25.0.dist-info/WHEEL
ws_api-0.25.0.dist-info/top_level.txt
ws_api-0.25.0.dist-info/RECORD
