Metadata-Version: 2.4
Name: WS-API
Version: 0.25.0
Summary: Access your Wealthsimple account using their (GraphQL) API.
Home-page: https://github.com/gboudreau/ws-api-python
Author: Guillaume Boudreau
Author-email: guillaume@pommepause.com
License: GPL-3.0
Keywords: wealthsimple
Classifier: Development Status :: 3 - Alpha
Classifier: Intended Audience :: Developers
Classifier: Operating System :: OS Independent
Classifier: License :: OSI Approved :: GNU General Public License v3 or later (GPLv3+)
Classifier: Programming Language :: Python :: 3
Classifier: Programming Language :: Python :: 3.13
Requires-Python: >=3.10
License-File: LICENSE
Requires-Dist: requests
Dynamic: author
Dynamic: author-email
Dynamic: classifier
Dynamic: home-page
Dynamic: keywords
Dynamic: license
Dynamic: license-file
Dynamic: requires-dist
Dynamic: requires-python
Dynamic: summary
